{
  "__comment": "Granted when you enter a Palace",
  "display": {
      "title": {
          "text": "Before The Flood"
      },
      "description": [
        {
          "text": "Enter a Palace"
        },
        {
          "color": "gray",
          "text": "\n \nReward:"
        },
        {
          "color": "yellow",
          "text": "\n25 XP"
        }
      ],
      "icon": {
          "id": "minecraft:sea_lantern"
      },
      "frame": "task",
      "show_toast": true,
      "announce_to_chat": true,
      "hidden": false
  },
  "criteria": {
    "palace": {
      "trigger": "minecraft:location",
      "conditions": {
        "player": [
          {
            "condition": "minecraft:entity_properties",
            "entity": "this",
            "predicate": {
              "location": {
                "structure": "atrium:dungeons/palace"
              }
            }
          }
        ]
      }
    }
  },
  "rewards": {
      "experience": 25
  },
  "parent": "atrium:abyss/under_pressure"
}