{
  "type": "chest",
  "pools": [
    {
      "rolls": 3,
      "bonus_rolls": 1,
      "entries": [
        {
          "type": "item",
          "weight": 1,
          "quality": -1,
          "name": "minecraft:suspicious_stew",
          "functions": [
            {
              "function": "set_components",
              "components": {
                "minecraft:suspicious_stew_effects": [
                  {
                    "id": "minecraft:nausea",
                    "duration": 40
                  }
                ]
              }
            }
          ]
        },
        {
          "type": "item",
          "weight": 1,
          "quality": 1,
          "name": "minecraft:mushroom_stew"
        },
        {
          "type": "item",
          "weight": 1,
          "quality": -1,
          "name": "minecraft:bowl"
        },
        {
          "type": "item",
          "weight": 2,
          "quality": -1,
          "name": "minecraft:lantern"
        },
        {
          "type": "item",
          "weight": 2,
          "quality": 0,
          "name": "minecraft:iron_pickaxe",
          "functions": [
            {
              "function": "set_damage",
              "damage": {
                "min": 0.3,
                "max": 0.65
              }
            }
          ]
        },
        {
          "type": "item",
          "weight": 1,
          "quality": 1,
          "name": "minecraft:lead",
          "functions": [
            {
              "function": "set_count",
              "count": {
                "min": 1,
                "max": 2
              }
            }
          ]
        },
        {
          "type": "item",
          "weight": 2,
          "quality": 0,
          "name": "minecraft:melon",
          "functions": [
            {
              "function": "set_count",
              "count": {
                "min": 1,
                "max": 2
              }
            }
          ]
        }
      ]
    },
    {
      "rolls": 14,
      "bonus_rolls": 0,
      "entries": [
        {
          "type": "item",
          "weight": 3,
          "name": "minecraft:vine"
        },
        {
          "type": "item",
          "weight": 2,
          "quality": 0,
          "name": "minecraft:stick"
        },
        {
          "type": "item",
          "weight": 5,
          "quality": 0,
          "name": "minecraft:jungle_leaves",
          "functions": [
            {
              "function": "set_count",
              "count": 2
            }
          ]
        }
      ]
    }
  ]
}