{
    "type": "minecraft:chest",
    "pools": [
      {
        "rolls": {
          "type": "minecraft:uniform",
          "min": 4,
          "max": 9
        },
        "bonus_rolls": 1,
        "entries": [
          {
            "type": "minecraft:item",
            "name": "minecraft:enchanted_golden_apple",
            "functions": [
              {
                "function": "minecraft:set_count",
                "count": {
                  "type": "minecraft:uniform",
                  "min": 1,
                  "max": 2
                },
                "add": false
              }
            ]
          },
          {
            "type": "minecraft:item",
            "name": "minecraft:book",
            "functions": [
              {
                "function": "minecraft:enchant_with_levels",
                "levels": {
                  "type": "minecraft:uniform",
                  "min": 35,
                  "max": 55
                },
                "treasure": true
              }
            ]
          },
          {
            "type": "minecraft:item",
            "weight": 2,
            "name": "minecraft:clock",
            "functions": [
              {
                "function": "minecraft:set_count",
                "count": 1,
                "add": false
              }
            ]
          },
          {
            "type": "minecraft:item",
            "weight": 2,
            "name": "minecraft:amethyst_shard",
            "functions": [
              {
                "function": "minecraft:set_count",
                "count": {
                  "type": "minecraft:uniform",
                  "min": 1,
                  "max": 2
                },
                "add": false
              }
            ]
          },
          {
            "type": "minecraft:item",
            "weight": 2,
            "name": "minecraft:name_tag"
          },
          {
            "type": "minecraft:item",
            "weight": 2,
            "name": "minecraft:diamond_sword",
            "functions": [
              {
                "function": "minecraft:set_count",
                "count": 1,
                "add": false
              },
              {
                "function": "minecraft:set_damage",
                "damage": {
                  "type": "minecraft:uniform",
                  "min": 0.8,
                  "max": 1
                },
                "add": false
              },
              {
                "function": "minecraft:enchant_with_levels",
                "levels": {
                  "type": "minecraft:uniform",
                  "min": 30,
                  "max": 50
                },
                "treasure": true
              }
            ]
          },
          {
            "type": "minecraft:item",
            "weight": 2,
            "name": "minecraft:lead",
            "functions": [
              {
                "function": "minecraft:set_count",
                "count": 1,
                "add": false
              }
            ]
          },
          {
            "type": "minecraft:item",
            "weight": 2,
            "name": "minecraft:diamond",
            "functions": [
                {
                    "function": "minecraft:set_count",
                    "count": {
                      "type": "minecraft:uniform",
                      "min": 1,
                      "max": 5
                    },
                    "add": false
                }
            ]
          },
          {
            "type": "minecraft:item",
            "weight": 2,
            "name": "minecraft:potion",
            "functions": [
              {
                "function": "minecraft:set_count",
                "count": {
                  "type": "minecraft:uniform",
                  "min": 1,
                  "max": 3
                },
                "add": false
              },
              {
                "function": "minecraft:set_potion",
                "id": "minecraft:long_slow_falling"
              }
            ]
          },
          {
            "type": "minecraft:item",
            "weight": 2,
            "name": "minecraft:diamond_helmet",
            "functions": [
              {
                "function": "minecraft:enchant_with_levels",
                "levels": {
                  "type": "minecraft:uniform",
                  "min": 30,
                  "max": 50
                },
                "treasure": true
              }
            ]
          },
          {
            "type": "minecraft:item",
            "weight": 2,
            "name": "minecraft:diamond_chestplate",
            "functions": [
              {
                "function": "minecraft:enchant_with_levels",
                "levels": {
                  "type": "minecraft:uniform",
                  "min": 30,
                  "max": 50
                },
                "treasure": true
              }
            ]
          },
          {
            "type": "minecraft:item",
            "weight": 2,
            "name": "minecraft:diamond_leggings",
            "functions": [
              {
                "function": "minecraft:enchant_with_levels",
                "levels": {
                  "type": "minecraft:uniform",
                  "min": 30,
                  "max": 50
                },
                "treasure": true
              }
            ]
          },
          {
            "type": "minecraft:item",
            "weight": 3,
            "name": "minecraft:book",
            "functions": [
              {
                "function": "minecraft:enchant_randomly",
                "enchantments": [
                  "minecraft:swift_sneak"
                ]
              }
            ]
          },
          {
            "type": "minecraft:item",
            "weight": 3,
            "name": "minecraft:lapis_lazuli",
            "functions": [
              {
                "function": "minecraft:set_count",
                "count": {
                  "type": "minecraft:uniform",
                  "min": 4,
                  "max": 10
                },
                "add": false
              }
            ]
          },
          {
            "type": "minecraft:item",
            "weight": 3,
            "name": "minecraft:writable_book"
          },
          {
            "type": "minecraft:item",
            "weight": 3,
            "name": "minecraft:white_candle",
            "functions": [
              {
                "function": "minecraft:set_count",
                "count": {
                  "type": "minecraft:uniform",
                  "min": 1,
                  "max": 8
                },
                "add": false
              }
            ]
          },
          {
            "type": "minecraft:item",
            "weight": 3,
            "name": "minecraft:amethyst_shard",
            "functions": [
              {
                "function": "minecraft:set_count",
                "count": {
                  "type": "minecraft:uniform",
                  "min": 1,
                  "max": 15
                },
                "add": false
              }
            ]
          },
          {
            "type": "minecraft:item",
            "weight": 3,
            "name": "minecraft:experience_bottle",
            "functions": [
              {
                "function": "minecraft:set_count",
                "count": {
                  "type": "minecraft:uniform",
                  "min": 2,
                  "max": 8
                },
                "add": false
              }
            ]
          },
          {
            "type": "minecraft:item",
            "weight": 1,
            "name": "minecraft:diamond_hoe",
            "functions": [
                {
                    "function": "minecraft:set_nbt",
                    "tag": "{display:{Name:'{\"text\":\"Staff of Air\",\"italic\":false}',Lore:['{\"text\":\"◇ Air Sigil I\",\"color\":\"gray\",\"italic\":false}','{\"text\":\"◇ Increase Velocity I\",\"color\":\"gray\",\"italic\":false}','{\"text\":\" \"}','{\"text\":\"When in Off Hand:\",\"color\":\"gray\",\"italic\":false}','{\"text\":\"+1 Casting Power\",\"color\":\"blue\",\"italic\":false}']},CustomModelData:333060,atrium_staff:1b,atrium_staff_lv:1b,atrium_air_staff:1b,atrium_chargeable:1b,AttributeModifiers:[{AttributeName:\"generic.attack_damage\",Name:\"generic.attack_damage\",Amount:2,Operation:0,UUID:[I;637717026,1710441391,-1943706047,783506473],Slot:\"mainhand\"}]}"
                }
            ]
          },
          {
            "type": "minecraft:item",
            "weight": 1,
            "name": "minecraft:diamond_hoe",
            "functions": [
                {
                  "function": "minecraft:set_nbt",
                  "tag": "{display:{Name:'{\"text\":\"Staff of Earth\",\"italic\":false}',Lore:['{\"text\":\"◇ Earth Sigil I\",\"color\":\"gray\",\"italic\":false}','{\"text\":\"◇ Natural Armor I\",\"color\":\"gray\",\"italic\":false}','{\"text\":\" \"}','{\"text\":\"When in Off Hand:\",\"color\":\"gray\",\"italic\":false}','{\"text\":\"+1 Casting Power\",\"color\":\"blue\",\"italic\":false}']},CustomModelData:333061,atrium_staff:1b,atrium_staff_lv:1b,atrium_earth_staff:1b,atrium_chargeable:1b,AttributeModifiers:[{AttributeName:\"generic.attack_damage\",Name:\"generic.attack_damage\",Amount:2,Operation:0,UUID:[I;637717026,1710441391,-1943706047,783506473],Slot:\"mainhand\"}]}"
                }
              ]
          },
          {
            "type": "minecraft:item",
            "weight": 1,
            "name": "minecraft:diamond_hoe",
            "functions": [
                {
                    "function": "minecraft:set_nbt",
                    "tag": "{display:{Name:'{\"text\":\"Staff of Fire\",\"italic\":false}',Lore:['{\"text\":\"◇ Fire Sigil I\",\"color\":\"gray\",\"italic\":false}','{\"text\":\"◇ Throw Flames I\",\"color\":\"gray\",\"italic\":false}','{\"text\":\" \"}','{\"text\":\"When in Off Hand:\",\"color\":\"gray\",\"italic\":false}','{\"text\":\"+1 Casting Power\",\"color\":\"blue\",\"italic\":false}']},CustomModelData:333062,atrium_staff:1b,atrium_staff_lv:1b,atrium_fire_staff:1b,atrium_chargeable:1b,AttributeModifiers:[{AttributeName:\"generic.attack_damage\",Name:\"generic.attack_damage\",Amount:2,Operation:0,UUID:[I;637717026,1710441391,-1943706047,783506473],Slot:\"mainhand\"}]}"
                }
            ]
          },
          {
            "type": "minecraft:item",
            "weight": 1,
            "name": "minecraft:diamond_hoe",
            "functions": [
                {
                    "function": "minecraft:set_nbt",
                    "tag": "{display:{Name:'{\"text\":\"Staff of Water\",\"italic\":false}',Lore:['{\"text\":\"◇ Water Sigil I\",\"color\":\"gray\",\"italic\":false}','{\"text\":\"◇ Extinguish I\",\"color\":\"gray\",\"italic\":false}','{\"text\":\" \"}','{\"text\":\"When in Off Hand:\",\"color\":\"gray\",\"italic\":false}','{\"text\":\"+1 Casting Power\",\"color\":\"blue\",\"italic\":false}']},CustomModelData:333063,atrium_staff:1b,atrium_staff_lv:1b,atrium_water_staff:1b,atrium_chargeable:1b,AttributeModifiers:[{AttributeName:\"generic.attack_damage\",Name:\"generic.attack_damage\",Amount:2,Operation:0,UUID:[I;637717026,1710441391,-1943706047,783506473],Slot:\"mainhand\"}]}"
                }
            ]
          },
          {
            "type": "minecraft:item",
            "weight": 1,
            "name": "minecraft:diamond_hoe",
            "functions": [
                {
                    "function": "minecraft:set_nbt",
                    "tag": "{display:{Name:'{\"text\":\"Staff of Time\",\"italic\":false}',Lore:['{\"text\":\"◇ Time Sigil I\",\"color\":\"gray\",\"italic\":false}','{\"text\":\"◇ Desync I\",\"color\":\"gray\",\"italic\":false}','{\"text\":\" \"}','{\"text\":\"When in Off Hand:\",\"color\":\"gray\",\"italic\":false}','{\"text\":\"+1 Casting Power\",\"color\":\"blue\",\"italic\":false}']},CustomModelData:333064,atrium_staff:1b,atrium_staff_lv:1b,atrium_time_staff:1b,atrium_chargeable:1b,AttributeModifiers:[{AttributeName:\"generic.attack_damage\",Name:\"generic.attack_damage\",Amount:2,Operation:0,UUID:[I;637717026,1710441391,-1943706047,783506473],Slot:\"mainhand\"}]}"
                }
            ]
          },
          {
            "type": "minecraft:item",
            "weight": 1,
            "name": "minecraft:diamond_hoe",
            "functions": [
                {
                    "function": "minecraft:set_nbt",
                    "tag": "{display:{Name:'{\"text\":\"Staff of Space\",\"italic\":false}',Lore:['{\"text\":\"◇ Space Sigil I\",\"color\":\"gray\",\"italic\":false}','{\"text\":\"◇ Parallax I\",\"color\":\"gray\",\"italic\":false}','{\"text\":\" \"}','{\"text\":\"When in Off Hand:\",\"color\":\"gray\",\"italic\":false}','{\"text\":\"+1 Casting Power\",\"color\":\"blue\",\"italic\":false}']},CustomModelData:333065,atrium_staff:1b,atrium_staff_lv:1b,atrium_space_staff:1b,atrium_chargeable:1b,AttributeModifiers:[{AttributeName:\"generic.attack_damage\",Name:\"generic.attack_damage\",Amount:2,Operation:0,UUID:[I;637717026,1710441391,-1943706047,783506473],Slot:\"mainhand\"}]}"
                }
            ]
          },
          {
            "type": "minecraft:item",
            "weight": 4,
            "name": "minecraft:echo_shard"
          },
          {
            "type": "minecraft:loot_table",
            "weight": 1,
            "name": "atrium:formulas/infusion_recipes_1"
          },
          {
            "type": "minecraft:loot_table",
            "weight": 1,
            "quality": 1,
            "name": "atrium:formulas/infusion_recipes_2"
          },
          {
            "type": "minecraft:loot_table",
            "weight": 1,
            "name": "atrium:formulas/runic_recipes_1"
          },
          {
            "type": "loot_table",
            "weight": 1,
            "quality": 1,
            "name": "atrium:formulas/runic_recipes_2"
          },
          {
            "type": "minecraft:item",
            "weight": 5,
            "name": "minecraft:potion",
            "functions": [
              {
                "function": "minecraft:set_count",
                "count": {
                  "type": "minecraft:uniform",
                  "min": 1,
                  "max": 3
                },
                "add": false
              },
              {
                "function": "minecraft:set_potion",
                "id": "minecraft:strong_regeneration"
              }
            ]
          },
          {
            "type": "minecraft:item",
            "weight": 5,
            "quality": 1,
            "name": "minecraft:book",
            "functions": [
              {
                "function": "minecraft:enchant_randomly"
              }
            ]
          },
          {
            "type": "minecraft:item",
            "weight": 5,
            "name": "minecraft:book",
            "functions": [
              {
                "function": "minecraft:set_count",
                "count": {
                  "type": "minecraft:uniform",
                  "min": 3,
                  "max": 10
                },
                "add": false
              }
            ]
          },
          {
            "type": "minecraft:item",
            "weight": 5,
            "name": "minecraft:bone",
            "functions": [
              {
                "function": "minecraft:set_count",
                "count": {
                  "type": "minecraft:uniform",
                  "min": 1,
                  "max": 15
                },
                "add": false
              }
            ]
          },
          {
            "type": "minecraft:item",
            "weight": 5,
            "name": "minecraft:soul_torch",
            "functions": [
              {
                "function": "minecraft:set_count",
                "count": {
                  "type": "minecraft:uniform",
                  "min": 1,
                  "max": 15
                },
                "add": false
              }
            ]
          },
          {
            "type": "minecraft:item",
            "weight": 7,
            "name": "minecraft:rotten_flesh",
            "functions": [
              {
                "function": "minecraft:set_count",
                "count": {
                  "type": "minecraft:uniform",
                  "min": 6,
                  "max": 15
                },
                "add": false
              }
            ]
          }
        ]
      }
    ],
    "random_sequence": "minecraft:chests/bastion_bridge"
  }
  