{
  "display": {
    "icon": {
      "item": "minecraft:tropical_fish_bucket"
    },
        "title": {
            "text": "Sunset Archipelago",
            "color": "dark_purple",
            "bold": false
        },
        "description": {
            "text": "Visit all vistas in Sunset Archipelago (across all planes)",
            "color": "green",
            "italic": true
        },
    "frame": "challenge",
    "show_toast": true,
    "announce_to_chat": true,
    "hidden": true
  },
  "parent": "atrium:old_server",
  "criteria": {
    "granted": {
        "trigger": "minecraft:impossible"
    }
}
}
